{
  "analysis_type": "market_intelligence",
  "data": {
    "pricing_trends": "Prices vary by season, generally higher in peak months (December and January) and lower in the off-peak season.",
    "booking_windows": "Best to book 2-3 months in advance for optimal prices, with last-minute deals occasionally available.",
    "demand": "Demand is particularly high during holiday seasons, with travelers showing interest in cultural experiences and natural wonders.",
    "competition": "Key competitors include Costa Rica and Mexico for eco-tourism and cultural experiences."
  },
  "saved_at": "2025-07-23T10:42:25.254Z"
}