{
  "requestId": "req_1752668415655_0buy9pxx71tp",
  "traceId": "api-1752668415655",
  "timestamp": "2025-07-16T12:20:15.655Z",
  "workflowType": "full-campaign",
  "currentPhase": "orchestration",
  "totalPhases": 5,
  "phaseIndex": 0,
  "campaign": {
    "id": "campaign_1752668415655",
    "name": "Зимнее путешествие в Марокко",
    "path": "",
    "brand": "Kupibilet",
    "language": "ru",
    "type": "promotional"
  },
  "execution": {
    "mode": "development",
    "apiRequest": true,
    "directSpecialistRun": false,
    "timeout": null,
    "maxTurns": 50,
    "retryAttempt": 0
  },
  "dataFlow": {
    "previousResults": {},
    "handoffData": null,
    "persistentState": {
      "apiEndpoint": "/api/agent/run-improved",
      "httpMethod": "POST",
      "userAgent": "curl/8.7.1",
      "clientIp": "::1",
      "destination": "Марокко",
      "origin": "Москва",
      "season": "зима",
      "language": "ru",
      "validationLevel": "standard",
      "qualityThreshold": 85
    },
    "correlationId": "corr_1752668415655_vm91nkw486",
    "handoffChain": []
  },
  "quality": {
    "validationLevel": "standard",
    "requiresApproval": true,
    "qualityThreshold": 85,
    "errorHandling": "fail-fast"
  },
  "monitoring": {
    "enableDebugOutput": true,
    "logLevel": "warn",
    "performanceTracking": true,
    "contextSnapshot": true,
    "additionalMetrics": {}
  },
  "extensions": {},
  "metadata": {
    "originalRequest": "Создать email кампанию для путешествия в Марокко зимой. Нужны авиабилеты из Москвы в Касабланку на зимний период с акцентом на экзотику и тепло.",
    "userAgent": "EmailMakers/3.1.0",
    "campaignName": "Зимнее путешествие в Марокко",
    "brand": "Kupibilet",
    "language": "ru",
    "campaignType": "promotional",
    "taskType": "generate_content",
    "endpoint": "/api/agent/run-improved",
    "inputType": "string",
    "apiRequest": true,
    "validationLevel": "standard",
    "qualityThreshold": 85,
    "destination": "Марокко",
    "origin": "Москва",
    "season": "зима",
    "originalOptions": {
      "traceId": "api-1752668415655",
      "metadata": {
        "campaignName": "Зимнее путешествие в Марокко",
        "brand": "Kupibilet",
        "language": "ru",
        "campaignType": "promotional",
        "taskType": "generate_content",
        "endpoint": "/api/agent/run-improved",
        "inputType": "string",
        "apiRequest": true,
        "validationLevel": "standard",
        "qualityThreshold": 85,
        "destination": "Марокко",
        "origin": "Москва",
        "season": "зима"
      },
      "context": {
        "apiEndpoint": "/api/agent/run-improved",
        "httpMethod": "POST",
        "userAgent": "curl/8.7.1",
        "clientIp": "::1",
        "destination": "Марокко",
        "origin": "Москва",
        "season": "зима",
        "language": "ru",
        "validationLevel": "standard",
        "qualityThreshold": 85
      }
    }
  }
}