{
  "actionable_insights": [
    "Highlight sustainable travel options in marketing campaigns",
    "Promote local cultural events and festivals",
    "Create packages focused on eco-tourism and adventure"
  ],
  "key_insights": [
    "Guatemala's rich culture and eco-tourism potential can attract more travelers",
    "Peak travel seasons should inform marketing efforts",
    "Pricing strategies need to adapt to seasonal demand"
  ],
  "confidence_score": 0.9,
  "analysis_timestamp": "2025-07-30T10:18:00.933Z",
  "saved_at": "2025-07-30T10:18:40.187Z"
}