{
  "analysis_type": "market_intelligence",
  "data": {
    "pricing_trends": "Average price for a week-long trip in the fall ranges from $800 to $1500 depending on accommodations and activities.",
    "booking_windows": "Best to book 2-3 months in advance for optimal prices and availability.",
    "demand": "Growing interest in cultural and adventure travel in Guatemala, particularly in the fall season.",
    "competition": "Other Central American destinations like Costa Rica and Belize but Guatemala offers unique cultural experiences."
  },
  "saved_at": "2025-07-30T07:13:53.642Z"
}