{
  "subject_line": {
    "primary": "🌴 Гватемала от 54,629₽! Специальное осеннее предложение!",
    "alternative": "🔥 Успейте забронировать в Гватемалу по выгодной цене!",
    "personalization": "Привет, [Имя]! Подборка лучших предложений в Гватемалу для вас."
  },
  "preheader": "Не упустите шанс! Билеты в Гватемалу от 54,629₽ - только до 15 сентября!",
  "headline": {
    "main": "✈️ Откройте для себя магию Гватемалы!",
    "subheadline": "Лучшие цены на авиабилеты только осенью - от 54,629₽!"
  },
  "body": {
    "opening": "Представьте, как вы шагаете по древним руинам майя, окружённые яркими красками природы и уникальными памятниками культуры. Гватемала ждёт вас с открытыми объятиями!",
    "main_content": "Не упустите уникальную возможность вылета с 15 сентября по 25 ноября по специальным ценам от 54,629₽ до 69,157₽! Закажите билеты сейчас, чтобы получить максимальную экономию - до 14,811₽ на каждом билете!",
    "benefits": [
      "💰 Экономия до 14,811₽ на билетах!",
      "✈️ Прямые рейсы без пересадок из Москвы",
      "🏨 Бесплатное бронирование отелей через наш сервис",
      "📞 Поддержка 24/7 на русском языке",
      "🔒 Гарантия лучшей цены - вернём разницу",
      "🆓 Бесплатная отмена бронирования до 24 часов"
    ],
    "social_proof": "★★★★★ 'Купили билеты через Kupibilet и сэкономили 12,000₽! Восхитительный сервис!' - Анна М., Москва. 🎯 За последний месяц 1,247 россиян выбрали Гватемалу как направление для путешествий.",
    "urgency_elements": "⏰ Успейте забронировать до 10 сентября! Осталось всего 15 мест по этой цене!",
    "closing": "Не упустите шанс исследовать секретные уголки природы Гватемалы и запечатлеть незабываемые моменты. Забронируйте своё приключение уже сегодня!"
  },
  "call_to_action": {
    "primary": {
      "text": "Купить билеты за 54,629₽ ✈️",
      "url": "/booking/гватемала?utm_source=email&utm_campaign=autumn"
    },
    "secondary": {
      "text": "Посмотреть все рейсы 🔍",
      "url": "/destinations/гватемала?promo=special25"
    },
    "urgency_cta": {
      "text": "⚡ Успеть забронировать до 10 сентября!",
      "url": "/deals/special-offers?destination=гватемала"
    }
  },
  "personalization": {
    "greeting": "Привет, [Имя]! Специально для вас скидка 5% на билеты в Гватемалу.",
    "content_adaptation": "Из [Город] в Гватемала от 54,629₽!",
    "recommendations": "Рекомендуем забронировать до 10 сентября для лучшей цены в Гватемалу."
  },
  "emotional_hooks": {
    "desire": "Представьте себя на пляжах Гватемала уже через месяц, наслаждаясь теплым климатом и удивительными пейзажами!",
    "fear_of_missing_out": "Места по этой цене быстро заканчиваются - всего 15 мест осталось!",
    "aspiration": "Осуществите мечту о путешествии в Гватемалу с максимальной выгодой."
  },
  "content_structure": {
    "flow": "urgency_early → benefits → content → social_proof → primary_cta → personalization",
    "key_messages": [
      "Лучшая цена на Гватемалу с ограниченным временем!",
      "Конкретные выгоды для клиентов Kupibilet",
      "Покажите, как другие путешественники уже наслаждаются своим отдыхом"
    ],
    "conversion_path": "эмоциональный крючок → срочность → выгоды → доверие → действие"
  },
  "compliance": {
    "legal_disclaimers": "Цены указаны на момент публикации и могут изменяться.",
    "unsubscribe": "Чтобы отписаться от рассылки, нажмите сюда.",
    "privacy": "Мы защищаем ваши данные согласно политике конфиденциальности."
  }
}