{
  "actionable_insights": [
    "Promote cultural festivals in targeted promotions during winter months.",
    "Emphasize eco-tourism opportunities to attract adventure seekers.",
    "Create package deals including flights and cultural experiences for better booking rates."
  ],
  "key_insights": [
    "Guatemala's winter offers unique cultural experiences that differentiate it from other winter destinations.",
    "The best times to promote trips are the months leading up to and during the dry season.",
    "Cultural immersion is a key desire among potential travelers to Guatemala."
  ],
  "confidence_score": 0.88,
  "analysis_timestamp": "2025-07-23T06:38:47.403Z",
  "saved_at": "2025-07-23T06:39:16.966Z"
}