{
  "analysis_type": "market_intelligence",
  "data": {
    "pricing_insights": "Весной рост цен на отели и авиабилеты до 40процентов, бюджет 90000-200000 руб",
    "competitive_position": "Япония уникальна по культуре и безопасности, конкуренты - Южная Корея, Гонконг",
    "demand_patterns": "Пик спроса с конца марта по середину апреля, бронируют за 2-4 месяца",
    "booking_recommendations": "Оптимально бронировать до декабря для лучших цен, рассматривать будние дни"
  },
  "saved_at": "2025-07-09T14:52:14.531Z"
}