{
  "analysis_type": "trend_analysis",
  "data": {
    "social_trends": "Фото цветущих оливковых рощ, гастро-туры, активности на природе, пешие прогулки, популярность афиш праздников в соцсетях",
    "booking_behaviors": "90 процентов бронирований онлайн, рост популярности комбинированных маршрутов и коротких city break",
    "emerging_opportunities": "Развитие эко-туризма, гастрономические и винные туры, экспериментальные авторские экскурсии, тренд на нетипичные острова",
    "content_opportunities": "Сторис с бодрым началом весны, семейные фото, советы по скрытым локациям, подборки блюд и рынков"
  },
  "saved_at": "2025-07-10T09:39:42.058Z"
}