{
  "visual_direction": {
    "primary_style": "Яркие и живые изображения, отражающие культуру и природу Гватемалы, с акцентом на приключения.",
    "color_palette": {
      "primary": "#E67E22",
      "secondary": "#2980B9",
      "accent": "#27AE60",
      "background": "#F4F4F4"
    },
    "imagery_style": "Фотографии местных жителей, культурных событий и природных пейзажей, с использованием натурального света.",
    "mood": "Приключенческий и вдохновляющий, создающий ощущение открытости и новых возможностей.",
    "visual_hierarchy": "Заголовок с крупным шрифтом, героическое изображение вверху, следом информация о направлении и ценах, завершающая часть с CTA."
  },
  "asset_types": [
    {
      "type": "hero-image",
      "description": "Визуально захватывающее изображение Гватемалы с пейзажами и культурными элементами.",
      "requirements": "Минимум 1200x800 пикселей, высокое разрешение.",
      "emotional_impact": "Создает чувство восхищения и желание посетить."
    },
    {
      "type": "destination-showcase",
      "description": "Слайд-шоу или галерея изображений, показывающая разнообразие Гватемалы.",
      "requirements": "Минимум 5 изображений, каждая около 800x600 пикселей.",
      "emotional_impact": "Пробуждает интерес к исследованию новых мест."
    },
    {
      "type": "price-highlight",
      "description": "Графика, подчеркивающая специальные предложения на билеты.",
      "requirements": "Четкий текст, визуально выделенные цены.",
      "emotional_impact": "Создает ощущение срочности и выгодной покупки."
    },
    {
      "type": "cta-buttons",
      "description": "Яркие кнопки с призывом к действию, например, 'Купить билет'.",
      "requirements": "Размер кнопок не менее 200x50 пикселей, контрастные цвета.",
      "emotional_impact": "Мотивирует немедленно действовать."
    },
    {
      "type": "supporting-visuals",
      "description": "Иконки или маленькие изображения, иллюстрирующие ключевые моменты поездки.",
      "requirements": "Малые размеры, согласованные с основной палитрой.",
      "emotional_impact": "Помогает визуализировать преимущества путешествия."
    }
  ],
  "content_strategy": {
    "tone": "Дружелюбный и вдохновляющий, вызывающий доверие.",
    "approach": "Рассказывать истории о путешествиях через культурные и природные аспекты Гватемалы.",
    "structure": "Введение с ярким заголовком, основная часть с интересным контентом и завершение с призывами к действию.",
    "key_messages": [
      "Откройте для себя культуру и природу Гватемалы.",
      "Специальные предложения на авиабилеты этой осенью!",
      "Путешествуйте с Kupibilet и создавайте незабываемые воспоминания."
    ],
    "emotional_triggers": [
      "Чувство приключения и открытия нового.",
      "Стремление к уникальным впечатлениям.",
      "Желание путешествовать и исследовать мир."
    ],
    "call_to_action": {
      "primary": "Купить билет сейчас",
      "secondary": "Узнать больше о Гватемале",
      "urgency": "Предложения ограничены по времени!"
    }
  },
  "targeting_insights": {
    "audience_motivations": [
      "Желание исследовать новые культуры.",
      "Поиск приключений и активного отдыха."
    ],
    "pain_points": [
      "Неопределенность в выборе направления.",
      "Боязнь высоких цен на билеты."
    ],
    "decision_factors": [
      "Цена билета.",
      "Уникальность предлагаемых впечатлений."
    ],
    "seasonal_considerations": "Осень - время, когда путешественники ищут новые впечатления перед зимним сезоном."
  },
  "technical_requirements": {
    "image_formats": [
      "JPEG",
      "PNG"
    ],
    "dimensions": "Минимум 600x400 пикселей для изображений.",
    "file_size_limits": "Не более 1MB для каждого изображения.",
    "accessibility": "Все изображения должны иметь альтернативный текст."
  },
  "success_metrics": {
    "primary_kpi": "Количество проданных билетов.",
    "engagement_metrics": [
      "Открываемость писем",
      "Клики по CTA"
    ],
    "conversion_indicators": [
      "Процент конверсии",
      "Средний чек"
    ]
  }
}