{
  "manifest": {
    "images": [
      {
        "id": "ai_1752216303527_gxvdnffr8lt",
        "path": "/Users/rtuzov/PycharmProjects/Email-Makers/campaigns/campaign_1752216115414_00f93fl72l8b/assets/optimized/optimized_иллюстрация-веселого-кролика-с-чемоданом-символизирующего-путешествия-и-отдых.png",
        "url": "/Users/rtuzov/PycharmProjects/Email-Makers/campaigns/campaign_1752216115414_00f93fl72l8b/assets/optimized/optimized_иллюстрация-веселого-кролика-с-чемоданом-символизирующего-путешествия-и-отдых.png",
        "alt_text": "AI-selected hero",
        "usage": "to capture the essence of autumn in Turkey and entice travelers with scenic views",
        "dimensions": {
          "width": 600,
          "height": 360
        },
        "file_size": 117414,
        "format": "png",
        "optimized": true,
        "isExternal": false,
        "email_client_support": {},
        "accessibility": {
          "alt_text_provided": true,
          "descriptive": true,
          "wcag_compliant": true
        },
        "performance": {
          "load_time_estimate": 117,
          "optimization_score": 80
        },
        "processed": true,
        "optimization_applied": "format_conversion_compression_and_resizing",
        "processing_timestamp": "2025-07-11T06:48:53.824Z",
        "technical_compliance": {
          "max_width_respected": true,
          "format_supported": false,
          "size_optimized": false
        }
      },
      {
        "id": "ai_1752216306339_dxslu390gn7",
        "path": "/Users/rtuzov/PycharmProjects/Email-Makers/campaigns/campaign_1752216115414_00f93fl72l8b/assets/optimized/optimized_информация-о-путешествии-из-владикавказа-в-санкт-петербург-с-указанием-цены.png",
        "url": "/Users/rtuzov/PycharmProjects/Email-Makers/campaigns/campaign_1752216115414_00f93fl72l8b/assets/optimized/optimized_информация-о-путешествии-из-владикавказа-в-санкт-петербург-с-указанием-цены.png",
        "alt_text": "AI-selected support",
        "usage": "to highlight specific locations in Turkey and indicate special offers and pricing",
        "dimensions": {
          "width": 600,
          "height": 360
        },
        "file_size": 76378,
        "format": "png",
        "optimized": true,
        "isExternal": false,
        "email_client_support": {},
        "accessibility": {
          "alt_text_provided": true,
          "descriptive": true,
          "wcag_compliant": true
        },
        "performance": {
          "load_time_estimate": 76,
          "optimization_score": 80
        },
        "processed": true,
        "optimization_applied": "format_conversion_compression_and_resizing",
        "processing_timestamp": "2025-07-11T06:48:53.824Z",
        "technical_compliance": {
          "max_width_respected": true,
          "format_supported": false,
          "size_optimized": true
        }
      },
      {
        "id": "ai_1752216306342_romk679w28k",
        "path": "/Users/rtuzov/PycharmProjects/Email-Makers/campaigns/campaign_1752216115414_00f93fl72l8b/assets/optimized/optimized_предложение-на-билет-дня-в-сочи-с-акционной-ценой.png",
        "url": "/Users/rtuzov/PycharmProjects/Email-Makers/campaigns/campaign_1752216115414_00f93fl72l8b/assets/optimized/optimized_предложение-на-билет-дня-в-сочи-с-акционной-ценой.png",
        "alt_text": "AI-selected support",
        "usage": "to highlight specific locations in Turkey and indicate special offers and pricing",
        "dimensions": {
          "width": 600,
          "height": 360
        },
        "file_size": 225968,
        "format": "png",
        "optimized": true,
        "isExternal": false,
        "email_client_support": {},
        "accessibility": {
          "alt_text_provided": true,
          "descriptive": true,
          "wcag_compliant": true
        },
        "performance": {
          "load_time_estimate": 226,
          "optimization_score": 80
        },
        "processed": true,
        "optimization_applied": "format_conversion_compression_and_resizing",
        "processing_timestamp": "2025-07-11T06:48:53.824Z",
        "technical_compliance": {
          "max_width_respected": true,
          "format_supported": false,
          "size_optimized": false
        }
      },
      {
        "id": "ai_1752216311680_0acn7gos68fl",
        "path": "/Users/rtuzov/PycharmProjects/Email-Makers/campaigns/campaign_1752216115414_00f93fl72l8b/assets/optimized/optimized_изображение-улыбающегося-смайлика-на-зеленом-фоне.png",
        "url": "/Users/rtuzov/PycharmProjects/Email-Makers/campaigns/campaign_1752216115414_00f93fl72l8b/assets/optimized/optimized_изображение-улыбающегося-смайлика-на-зеленом-фоне.png",
        "alt_text": "AI-selected decoration",
        "usage": "to add decorative elements that enhance the overall theme of relaxation and enjoyment",
        "dimensions": {
          "width": 600,
          "height": 360
        },
        "file_size": 19691,
        "format": "png",
        "optimized": true,
        "isExternal": false,
        "email_client_support": {},
        "accessibility": {
          "alt_text_provided": true,
          "descriptive": true,
          "wcag_compliant": true
        },
        "performance": {
          "load_time_estimate": 20,
          "optimization_score": 80
        },
        "processed": true,
        "optimization_applied": "format_conversion_compression_and_resizing",
        "processing_timestamp": "2025-07-11T06:48:53.824Z",
        "technical_compliance": {
          "max_width_respected": true,
          "format_supported": false,
          "size_optimized": true
        }
      }
    ],
    "icons": [
      {
        "id": "ai_1752216309836_mf86e2x1jl",
        "path": "/Users/rtuzov/PycharmProjects/Email-Makers/campaigns/campaign_1752216115414_00f93fl72l8b/assets/optimized/optimized_предложение-о-бонусах-и-акциях-для-клиентов.png",
        "url": "/Users/rtuzov/PycharmProjects/Email-Makers/campaigns/campaign_1752216115414_00f93fl72l8b/assets/optimized/optimized_предложение-о-бонусах-и-акциях-для-клиентов.png",
        "alt_text": "AI-selected icon",
        "usage": "to facilitate the booking process and indicate special offers",
        "dimensions": {
          "width": 0,
          "height": 0
        },
        "file_size": 4585,
        "format": "png",
        "optimized": true,
        "isExternal": false,
        "email_client_support": {},
        "accessibility": {
          "alt_text_provided": true,
          "descriptive": true,
          "wcag_compliant": true
        },
        "performance": {
          "load_time_estimate": 5,
          "optimization_score": 80
        },
        "processed": true,
        "optimization_applied": "format_conversion_compression_and_resizing",
        "processing_timestamp": "2025-07-11T06:48:53.824Z",
        "technical_compliance": {
          "format_supported": false,
          "size_optimized": true
        }
      },
      {
        "id": "ai_1752216309836_zx1dedfomvs",
        "path": "/Users/rtuzov/PycharmProjects/Email-Makers/campaigns/campaign_1752216115414_00f93fl72l8b/assets/optimized/optimized_эмодзи-символизирующий-радость-и-удовлетворение-от-покупки-билета.png",
        "url": "/Users/rtuzov/PycharmProjects/Email-Makers/campaigns/campaign_1752216115414_00f93fl72l8b/assets/optimized/optimized_эмодзи-символизирующий-радость-и-удовлетворение-от-покупки-билета.png",
        "alt_text": "AI-selected icon",
        "usage": "to facilitate the booking process and indicate special offers",
        "dimensions": {
          "width": 0,
          "height": 0
        },
        "file_size": 4011,
        "format": "png",
        "optimized": true,
        "isExternal": false,
        "email_client_support": {},
        "accessibility": {
          "alt_text_provided": true,
          "descriptive": true,
          "wcag_compliant": true
        },
        "performance": {
          "load_time_estimate": 4,
          "optimization_score": 80
        },
        "processed": true,
        "optimization_applied": "format_conversion_compression_and_resizing",
        "processing_timestamp": "2025-07-11T06:48:53.824Z",
        "technical_compliance": {
          "format_supported": false,
          "size_optimized": true
        }
      }
    ],
    "fonts": [
      {
        "id": "default-font",
        "family": "Arial, sans-serif",
        "weights": [
          "400",
          "700"
        ],
        "fallbacks": [
          "Helvetica",
          "sans-serif"
        ],
        "usage": "primary-text",
        "email_client_support": {
          "gmail": true,
          "outlook": true,
          "apple_mail": true,
          "yahoo_mail": true
        }
      }
    ]
  },
  "usage_instructions": [
    {
      "asset_id": "ai_1752216303527_gxvdnffr8lt",
      "asset_type": "image",
      "usage_context": "to capture the essence of autumn in Turkey and entice travelers with scenic views",
      "placement_instructions": "Place according to design specifications and content context",
      "responsive_behavior": "Scale proportionally for mobile devices, maintain aspect ratio",
      "accessibility_requirements": {
        "alt_text": "AI-selected hero",
        "wcag_compliant": true
      },
      "email_client_notes": [
        "Large file size may cause loading issues in some email clients"
      ],
      "performance_considerations": {
        "file_size": 117414,
        "load_time_estimate": "N/A",
        "optimization_applied": true
      }
    },
    {
      "asset_id": "ai_1752216306339_dxslu390gn7",
      "asset_type": "image",
      "usage_context": "to highlight specific locations in Turkey and indicate special offers and pricing",
      "placement_instructions": "Place according to design specifications and content context",
      "responsive_behavior": "Scale proportionally for mobile devices, maintain aspect ratio",
      "accessibility_requirements": {
        "alt_text": "AI-selected support",
        "wcag_compliant": true
      },
      "email_client_notes": [],
      "performance_considerations": {
        "file_size": 76378,
        "load_time_estimate": "N/A",
        "optimization_applied": true
      }
    },
    {
      "asset_id": "ai_1752216306342_romk679w28k",
      "asset_type": "image",
      "usage_context": "to highlight specific locations in Turkey and indicate special offers and pricing",
      "placement_instructions": "Place according to design specifications and content context",
      "responsive_behavior": "Scale proportionally for mobile devices, maintain aspect ratio",
      "accessibility_requirements": {
        "alt_text": "AI-selected support",
        "wcag_compliant": true
      },
      "email_client_notes": [
        "Large file size may cause loading issues in some email clients"
      ],
      "performance_considerations": {
        "file_size": 225968,
        "load_time_estimate": "N/A",
        "optimization_applied": true
      }
    },
    {
      "asset_id": "ai_1752216311680_0acn7gos68fl",
      "asset_type": "image",
      "usage_context": "to add decorative elements that enhance the overall theme of relaxation and enjoyment",
      "placement_instructions": "Place according to design specifications and content context",
      "responsive_behavior": "Scale proportionally for mobile devices, maintain aspect ratio",
      "accessibility_requirements": {
        "alt_text": "AI-selected decoration",
        "wcag_compliant": true
      },
      "email_client_notes": [],
      "performance_considerations": {
        "file_size": 19691,
        "load_time_estimate": "N/A",
        "optimization_applied": true
      }
    },
    {
      "asset_id": "ai_1752216309836_mf86e2x1jl",
      "asset_type": "icon",
      "usage_context": "to facilitate the booking process and indicate special offers",
      "placement_instructions": "Place as decorative element according to design specifications",
      "accessibility_requirements": {
        "alt_text": "AI-selected icon",
        "wcag_compliant": false
      },
      "email_client_notes": [],
      "performance_considerations": {
        "file_size": 4585,
        "optimization_applied": true
      }
    },
    {
      "asset_id": "ai_1752216309836_zx1dedfomvs",
      "asset_type": "icon",
      "usage_context": "to facilitate the booking process and indicate special offers",
      "placement_instructions": "Place as decorative element according to design specifications",
      "accessibility_requirements": {
        "alt_text": "AI-selected icon",
        "wcag_compliant": false
      },
      "email_client_notes": [],
      "performance_considerations": {
        "file_size": 4011,
        "optimization_applied": true
      }
    }
  ],
  "processing_summary": {
    "total_images": 4,
    "total_icons": 2,
    "optimization_level": "high",
    "processed_at": "2025-07-11T06:48:53.825Z"
  }
}