{
  "insight_type": "travel_intelligence",
  "insights": [
    "Турция осенью - мягкий климат, теплое море, меньше туристов, лучшие цены для российских путешественников",
    "Бренд Kupibilet - ассоциация с теплом, выгодой и доверием через цвета и визуал контента",
    "Для семей и пар лучшее восприятие кампании достигается эмоциями уюта и выгодой бронирования",
    "Пользователи ждут коротких, информативных рассылок с фото и четким CTA, особенно к пляжам и экскурсиям",
    "Осень - время экскурсий, SPA, кулинарных туров, новых мест: повышайте вовлеченность через свежие идеи",
    "Лучшие ценовые предложения и акции в сентябре-октябре: используйте точки планирования туров"
  ],
  "insights_count": 6,
  "saved_at": "2025-07-11T07:07:07.193Z",
  "file_path": "/Users/rtuzov/PycharmProjects/Email-Makers/campaigns/campaign_1752217555261_p051zohgqbf/data/travel_intelligence-insights.json"
}