{
  "analysis_type": "emotional_profile",
  "data": {
    "core_motivations": "Поиск комфортного и экзотического отдыха, возможность сбежать от повседневной рутины, укрепление семейных связей.",
    "emotional_triggers": "Солнце, пляжи, тропическая природа, яркие цвета тайской культуры, вкусная еда. Использование фотографий с пляжей для привлечения внимания в соцсетях.",
    "key_desires": "Экзотические путешествия, отдых на пляже, рассказ о своих приключениях в социальных сетях, неповторимые кулинарные впечатления.",
    "psychological_benefits": "Восстановление душевного равновесия, новые впечатления и социализация, возможность делиться опытом с друзьями и семьей."
  },
  "saved_at": "2025-07-12T01:55:43.433Z"
}