{
  "analysis_type": "destination_analysis",
  "data": {
    "climate_factors": "Осень в Париже мягкая, температура 10-18C, возможен дождь, красивые желтые листья",
    "cultural_highlights": "Лувр, Эйфелева башня, Монмартр, мода, винные бары, арт-галереи",
    "key_attractions": "Собор Парижской Богоматери, Версаль, улочки Марэ, музеи Орсе и Родена",
    "seasonal_advantages": "Меньше туристов, очереди короче, сезон акций на жилье, кафе и гастрономия"
  },
  "saved_at": "2025-07-09T14:39:17.612Z"
}