{
  "actionable_insights": [
    "Акцент на солнечных пляжах и тропиках даже в ноябре.",
    "Использовать истории и визуалы фестиваля Лой Кратонг.",
    "Подчеркнуть выгодную цену осени, выделить пакетные предложения и скидки.",
    "Рекомендовать как сбежать от российской осени и перезагрузиться.",
    "Продвигать индивидуальные туры и комбинированные маршруты.",
    "Добавить образы и цвета Kupibilet - ярко-зеленый, апельсиновый, фиолетовый для визуального и эмоционального единства.",
    "Играть на контрасте сезонных эмоций: холод в России, тепло и радость в Таиланде.",
    "Показать релакс, wellness, гастро и романтику под пальмами.",
    "Фокус на фото- и видеоконтент для соцсетей.",
    "Поддержать самостоятельный бронирования и умные советы."
  ],
  "key_insights": [
    "Осень в Таиланде - выгодно, тепло, мало туристов.",
    "Яркий культурный сезон и фестивали делают поездку особенной.",
    "Kupibilet цвета гармонируют с тропической атмосферой.",
    "Востребованы индивидуальные и авторские маршруты.",
    "Эмоциональный триггер осени - бегство от серых будней в тайское лето."
  ],
  "confidence_score": 0.95,
  "analysis_timestamp": "2025-07-10T09:00:16.003Z",
  "saved_at": "2025-07-10T09:00:46.629Z"
}