{
  "actionable_insights": [
    "Promote unique winter experiences in Karelia.",
    "Highlight packages that include local cuisine and spa treatments.",
    "Use social media to showcase real-time winter landscapes."
  ],
  "key_insights": [
    "Karelia's winter maintenance and safety assure travelers.",
    "Cultural experiences are a top priority for many visitors.",
    "Position Karelia as a quieter, less crowded alternative."
  ],
  "confidence_score": 0.88,
  "analysis_timestamp": "2025-07-23T08:25:35Z",
  "saved_at": "2025-07-23T08:26:01.224Z"
}